concrete_python-2.11.0.dist-info/RECORD
concrete_python-2.11.0.dist-info/WHEEL
concrete_python-2.11.0.dist-info/top_level.txt
concrete_python-2.11.0.dist-info/METADATA
concrete_python-2.11.0.dist-info/licenses/LICENSE
concrete/__init__.py
concrete/fhe/version.py
concrete/fhe/__init__.py
concrete/fhe/tracing/__init__.py
concrete/fhe/tracing/typing.py
concrete/fhe/tracing/tracer.py
concrete/fhe/values/scalar.py
concrete/fhe/values/__init__.py
concrete/fhe/values/tensor.py
concrete/fhe/values/value_description.py
concrete/fhe/internal/__init__.py
concrete/fhe/internal/utils.py
concrete/fhe/dtypes/float.py
concrete/fhe/dtypes/__init__.py
concrete/fhe/dtypes/integer.py
concrete/fhe/dtypes/utils.py
concrete/fhe/dtypes/base.py
concrete/fhe/mlir/conversion.py
concrete/fhe/mlir/converter.py
concrete/fhe/mlir/__init__.py
concrete/fhe/mlir/context.py
concrete/fhe/mlir/utils.py
concrete/fhe/mlir/operations/min_max.py
concrete/fhe/mlir/operations/assignment.py
concrete/fhe/mlir/operations/indexing.py
concrete/fhe/mlir/processors/process_rounding.py
concrete/fhe/mlir/processors/__init__.py
concrete/fhe/mlir/processors/assign_node_ids.py
concrete/fhe/mlir/processors/assign_bit_widths.py
concrete/fhe/mlir/processors/check_integer_only.py
concrete/fhe/extensions/bits.py
concrete/fhe/extensions/univariate.py
concrete/fhe/extensions/round_bit_pattern.py
concrete/fhe/extensions/convolution.py
concrete/fhe/extensions/zeros.py
concrete/fhe/extensions/__init__.py
concrete/fhe/extensions/truncate_bit_pattern.py
concrete/fhe/extensions/maxpool.py
concrete/fhe/extensions/relu.py
concrete/fhe/extensions/multivariate.py
concrete/fhe/extensions/table.py
concrete/fhe/extensions/constant.py
concrete/fhe/extensions/hint.py
concrete/fhe/extensions/array.py
concrete/fhe/extensions/identity.py
concrete/fhe/extensions/tag.py
concrete/fhe/extensions/ones.py
concrete/fhe/tfhers/specs.py
concrete/fhe/tfhers/tracing.py
concrete/fhe/tfhers/values.py
concrete/fhe/tfhers/bridge.py
concrete/fhe/tfhers/__init__.py
concrete/fhe/tfhers/dtypes.py
concrete/fhe/representation/graph.py
concrete/fhe/representation/__init__.py
concrete/fhe/representation/operation.py
