Metadata-Version: 2.4
Name: concrete-python
Version: 2.11.0
Summary: A state-of-the-art homomorphic encryption framework
Home-page: https://github.com/zama-ai/concrete/tree/main/frontends/concrete-python
Author: Zama
Author-email: hello@zama.ai
License: BSD-3-Clause
Keywords: fhe,homomorphic,encryption,tfhe,privacy,security
Classifier: Intended Audience :: Developers
Classifier: Intended Audience :: Science/Research
Classifier: Topic :: Security :: Cryptography
Classifier: Topic :: Software Development :: Compilers
Requires-Python: >=3.9
License-File: LICENSE
Requires-Dist: importlib-resources>=6.1
Requires-Dist: jsonpickle>=3.0.3
Requires-Dist: networkx>=2.6
Requires-Dist: numpy<2.0,>=1.23
Requires-Dist: scipy>=1.10
Requires-Dist: torch>=1.13
Requires-Dist: z3-solver==4.13.0
Provides-Extra: dev
Requires-Dist: pybind11==2.10.4; extra == "dev"
Requires-Dist: pytest-cov==4.0.0; extra == "dev"
Requires-Dist: pytest-randomly==3.15.0; extra == "dev"
Requires-Dist: pytest-xdist==3.2.1; extra == "dev"
Requires-Dist: pytest==7.2.2; extra == "dev"
Requires-Dist: black==24.4.0; extra == "dev"
Requires-Dist: isort==5.12.0; extra == "dev"
Requires-Dist: mypy==1.10.0; extra == "dev"
Requires-Dist: pydocstyle==6.3.0; extra == "dev"
Requires-Dist: pylint==2.17.1; extra == "dev"
Requires-Dist: ruff==0.6.3; extra == "dev"
Requires-Dist: auditwheel==6.3.0; sys_platform == "linux" and extra == "dev"
Requires-Dist: delocate==0.10.4; sys_platform == "darwin" and extra == "dev"
Requires-Dist: wheel==0.40.0; extra == "dev"
Requires-Dist: py-progress-tracker==0.7.0; extra == "dev"
Requires-Dist: linkcheckmd>=1.4.0; extra == "dev"
Requires-Dist: linkchecker>=10.3.0; extra == "dev"
Requires-Dist: mistletoe>=0.9.0; extra == "dev"
Requires-Dist: pygame>=2.6.0; extra == "dev"
Requires-Dist: notebook>=7.2.2; extra == "dev"
Requires-Dist: matplotlib>=3.7; extra == "dev"
Requires-Dist: pillow>=10.2; extra == "dev"
Requires-Dist: pygraphviz>=1.11; extra == "dev"
Provides-Extra: full
Requires-Dist: matplotlib>=3.7; extra == "full"
Requires-Dist: pillow>=10.2; extra == "full"
Requires-Dist: pygraphviz>=1.11; extra == "full"
Dynamic: author
Dynamic: author-email
Dynamic: classifier
Dynamic: description
Dynamic: description-content-type
Dynamic: home-page
Dynamic: keywords
Dynamic: license
Dynamic: license-file
Dynamic: provides-extra
Dynamic: requires-dist
Dynamic: requires-python
Dynamic: summary
